redditquotebot/__init__.py
redditquotebot/backtesting.py
redditquotebot/bot_builder.py
redditquotebot/reddit_quote_bot.py
redditquotebot/data/__init__.py
redditquotebot/data/quotes.csv
redditquotebot/nlp/__init__.py
redditquotebot/nlp/matched_quote.py
redditquotebot/nlp/quote_comment_matcher.py
redditquotebot/nlp/quote_detector.py
redditquotebot/quotes/__init__.py
redditquotebot/quotes/quote.py
redditquotebot/quotes/quote_db.py
redditquotebot/quotes/quote_filter.py
redditquotebot/quotes/quote_loader.py
redditquotebot/reddit/__init__.py
redditquotebot/reddit/comment.py
redditquotebot/reddit/comment_filter.py
redditquotebot/reddit/exceptions.py
redditquotebot/reddit/reddit.py
redditquotebot/reddit/reply.py
redditquotebot/utilities/__init__.py
redditquotebot/utilities/configuration.py
redditquotebot/utilities/credential_store.py
redditquotebot/utilities/delayed_keyboard_interrupt.py
redditquotebot/utilities/file_associator.py
redditquotebot/utilities/logger.py
redditquotebot/utilities/record_keeper.py
redditquotebot/utilities/scrape_state.py
redditquotebot/utilities/time_delta.py
redditquotebot-0.4.0.data/scripts/reddit_quote_bot.py
redditquotebot-0.4.0.data/scripts/rqb_record_combine.py
tests/__init__.py
tests/test_backtesting.py
tests/test_bot_builder.py
tests/test_reddit_quote_bot.py
tests/nlp/__init__.py
tests/nlp/test_matched_quote.py
tests/nlp/test_quote_comment_matcher.py
tests/nlp/test_quote_detector.py
tests/quotes/__init__.py
tests/quotes/test_quote.py
tests/quotes/test_quote_db.py
tests/quotes/test_quote_filter.py
tests/quotes/test_quote_loader.py
tests/reddit/__init__.py
tests/reddit/test_comment.py
tests/reddit/test_comment_filter.py
tests/reddit/test_reply.py
tests/utilities/__init__.py
tests/utilities/test_configuration.py
tests/utilities/test_credential_store.py
tests/utilities/test_file_associator.py
tests/utilities/test_record_keeper.py
tests/utilities/test_scrape_state.py
tests/utilities/test_time_delta.py
redditquotebot-0.4.0.dist-info/LICENCE.md
redditquotebot-0.4.0.dist-info/METADATA
redditquotebot-0.4.0.dist-info/WHEEL
redditquotebot-0.4.0.dist-info/top_level.txt
redditquotebot-0.4.0.dist-info/RECORD
