Metadata-Version: 2.1
Name: redditquotebot
Version: 0.4.0
Summary: Reddit bot for detecting and replying to famous quotes
Home-page: UNKNOWN
Author: Porthos
Author-email: etdds@protonmail.com
License: UNKNOWN
Platform: UNKNOWN
Classifier: Programming Language :: Python :: 3
Classifier: Operating System :: OS Independent
Requires-Python: >=3.6
License-File: LICENCE.md
Requires-Dist: praw (==7.6.0)
Requires-Dist: spacy (==3.4.2)
